pylond/__init__.py
pylond/countries.py
pylond/languages.py
pylond/mutual.py
pylond-0.2.0.dist-info/licenses/LICENSE
pylond-0.2.0.dist-info/METADATA
pylond-0.2.0.dist-info/WHEEL
pylond-0.2.0.dist-info/top_level.txt
pylond-0.2.0.dist-info/RECORD
